Metadata-Version: 2.1
Name: audino_cvat_sdk
Version: 2.21.0
Summary: Audino CVAT REST API
Home-page: https://github.com/midas-research/cvat
Author: Audino team
Author-email: contact@audino.in
License: MIT License
Keywords: OpenAPI,OpenAPI-Generator,Audino CVAT REST API
Classifier: Programming Language :: Python :: 3
Classifier: License :: OSI Approved :: MIT License
Classifier: Operating System :: OS Independent
Requires-Python: >=3.8
Requires-Dist: attrs>=21.4.0
Requires-Dist: packaging>=21.3
Requires-Dist: Pillow>=10.3.0
Requires-Dist: platformdirs>=2.1.0
Requires-Dist: tqdm>=4.64.0
Requires-Dist: tuspy==0.2.5
Requires-Dist: typing-extensions>=4.2.0
Requires-Dist: python-dateutil>=2.5.3
Requires-Dist: setuptools>=21.0.0
Requires-Dist: urllib3>=1.25.3
Provides-Extra: pytorch
Requires-Dist: torch; extra == "pytorch"
Requires-Dist: torchvision; extra == "pytorch"
